{
  "hello": "hallo",
  "Login": "Anmelden",
  "Sign up": "Registrieren",
  "Home": "Startseite",
  "Sports": "Sport",
  "Casino": "Casino",
  "Lottery": "Lotterie",
  "Jackpot": "Jackpot",
  "Chess": "Schach",
  "Slot": "Spielautomat",
  "Welcome to our website": "Willkommen auf unserer Website",
  "Learn more": "Mehr erfahren",
  "Contact us": "Kontaktieren Sie uns",
  "About us": "Über uns",

"Terms and Conditions": "Allgemeine Geschäftsbedingungen",
  "Live Support": "Live-Support",
  "Virtual": "Virtuell",
  "Deposit": "Einzahlung",
  "Withdraw": "Auszahlung",
  "History": "Verlauf",
  "Settings": "Einstellungen",
  "Help": "Hilfe",
  "All Games": "Alle Spiele",
  "About Us": "Über uns",
  "General Bonuses Terms": "Allgemeine Bonusbedingungen",
  "Privacy Policy": "Datenschutzrichtlinie",
  "Additional info": "Zusätzliche Informationen",
  "Affiliates": "Partner",
  "Ambassadors": "Botschafter",
  "Source of Information": "Informationsquelle",
  "Games": "Spiele",
  "Chess & Cards": "Schach & Karten",
  "Virtual Games": "Virtuelle Spiele",
  "Top Played Lottery": "Meistgespielte Lotterie",
  "Aviator": "Flieger",
  "Bonus buy": "Bonus kaufen",
  "Soccer": "Fußball",
  "Live Bet": "Live-Wette",
  "Community": "Gemeinschaft",
  "X/Twitter": "X/Twitter",
  "Telegram": "Telegram",
  "Discord": "Discord",
  "Blog": "Blog",
  "Instagram": "Instagram",
  "Facebook": "Facebook",
  "FAQ": "Häufig gestellte Fragen",
  "General Sportsbook": "Allgemeine Sportwetten",
  "Help Center": "Hilfezentrum",
  "Betting Rules": "Wettregeln",
  "Responsible Gaming": "Verantwortungsbewusstes Spielen",
  "Contact Us": "Kontaktieren Sie uns",
  "Slots": "Spielautomaten",
  "About Cryptocurrency": "Über Kryptowährung",
  "Game Type": "Spieltyp",
  "Sub Game Type": "Unterspieltyp",
  "Hall of Fame": "Ruhmeshalle",
  "Cricket": "Kricket",
  "Top Rated Games": "Bestbewertete Spiele",
  "Top Rated Sports": "Bestbewertete Sportarten",
  "Top Rated Casino": "Bestbewertetes Casino",
  "Top Rated Lottery": "Bestbewertete Lotterie",
  "Top Played Games": "Meistgespielte Spiele",
  "Grand Prize Winners": "Hauptpreisgewinner",
  "Recent": "Neueste",
  "Favorite": "Favorit",
  "Search": "Suche",
  "Top Winners": "Top-Gewinner",
  "BET": "Wette",
  "MULTIPLIER": "Multiplikator",
  "PAYOUT": "Auszahlung",
  "PLAYER": "Spieler",
  "Game": "Spiel",
  "Username": "Benutzername",
  "Password": "Passwort",
  "Confirm Password": "Passwort bestätigen",
  "Forgot Password": "Passwort vergessen?",
  "Sign in": "Anmelden",
  "Register": "Registrieren",
  "Already have an account? Sign in": "Sie haben bereits ein Konto? Anmelden",
  "Create an account": "Konto erstellen",
  "Back to login": "Zurück zur Anmeldung",
  "Email": "E-Mail",
  "Currency": "Währung",
  "Language": "Sprache",
  "Change Password": "Passwort ändern",
  "Current Password": "Aktuelles Passwort",
  "New Password": "Neues Passwort",
  "Confirm New Password": "Neues Passwort bestätigen",
  "Change": "Ändern",
  "Account Settings": "Kontoeinstellungen",
  "Profile": "Profil",
  "Logout": "Abmelden",
  "Change Email": "E-Mail ändern",
  "Change Phone Number": "Telefonnummer ändern",
"Security Settings": "Sicherheitseinstellungen",
  "Two-Factor Authentication": "Zwei-Faktor-Authentifizierung",
  "Enable Two-Factor Authentication": "Zwei-Faktor-Authentifizierung aktivieren",
  "Disable Two-Factor Authentication": "Zwei-Faktor-Authentifizierung deaktivieren",
  "Enable": "Aktivieren",
  "The most recognizable recent winner": "Der bekannteste jüngste Gewinner",
  "Disable": "Deaktivieren",
  "Select Game Type": "Spieltyp auswählen",
  "Select Sub Game Type": "Unterspieltyp auswählen",
  "Basketball": "Basketball",

  "Baseball": "Baseball",
  "Ping Pong": "Tischtennis",
  "Table Tennis": "Tischtennis",
  "Add to Cart": "In den Warenkorb legen",
  "Type": "Typ",
  "Betting Content": "Wetttinhalt",
  "Number of Bets": "Anzahl der Wetten",
  "Units": "Einheiten",
  "Multiple": "Vielfaches",
  "Bet Amount": "Wettbetrag (Euro)",
  "Control": "Löschen",
  "For Sale": "Zum Verkauf",
  "No": "Nr.",
  "Upload File": "Datei hochladen",
  "All": "Alle",
  "Clear": "Löschen",
  "Hot/Cold": "Heiß/Kalt",
  "Lack": "Fehlend",
  "Prize": "Preis",
  "Standard": "Standard",
  "Two Sides": "Zwei Seiten",
  "Trend": "Trend",
  "Roadbet": "Straßenwette",
  "Long Dragon": "Langer Drache",
  "Many Tables": "Viele Tische",
  "1st": "1.",
  "2nd": "2.",
  "3rd": "3.",
  "4th": "4.",
  "5th": "5.",
  "Big": "Groß",
  "Small": "Klein",
  "Even": "Gerade",
  "Odd": "Ungerade",
  "Select Place": "Ort auswählen"
}