{
  "Type": "Loại",
  "Selections": "Lựa chọn",
  "Amount": "Số tiền",
  "Profit": "Lợi nhuận",
  "3rd Big/Small": "Lợi nhuận",
  "Sum Odd/Even": "Tổng Lẻ/ Chẵn",
  "Sum Big/Small": "Tổng Lớn/ Nhỏ",
  "Sum Dragon/Tiger/Tie": "Tổng Rồng/Hổ/Hòa",
  "Dragon": "Rồng",
  "Tiger": "Hổ",
  "Tie": "Hòa",
  "Prime": "Số nguyên tố",
  "Composite": "Số hợp thành",
  "1st Big/Small": "1st Lớn/ Nhỏ",
  "Big": "Lớn",
  "Small": "Nhỏ",
  "1st Odd/Even": "1st Lẻ/ Chẵn",
  "Odd": "Lẻ",
  "Even": "Chẵn",

  "1st Dragon/Tiger/Tie": "1 Rồng/Hổ/Hòa",
  "1st P/C": "P/C đầu tiên",
  "2nd P/C": "P/C thứ 2",
  "2nd Big/Small": "Lớn/Nhỏ thứ 2",
  "2nd Odd/Even": "Chẵn/Lẻ thứ 2",
  "2nd Dragon/Tiger/Tie": "Rồng/Hổ/Hòa thứ 2",
  "3rd Odd/Even": "Chẵn/Lẻ thứ 3",
  "3rd Dragon/Tiger/Tie": "Rồng/Hổ/Hòa thứ 3",
  "4th P/C": "P/C thứ 4",
  "4th Dragon/Tiger/Tie": "Rồng/Hổ/Hòa thứ 4",
  "4th Odd/Even": "Chẵn/Lẻ thứ 4",
  "4th Big/Small": "Lớn/Nhỏ thứ 4",
  "5th P/C": "P/C thứ 5",
  "5th Dragon/Tiger/Tie": "Rồng/Hổ/Hòa thứ 5",
  "5th Odd/Even": "Chẵn/Lẻ thứ 5",
  "5th Big/Small": "5 Lớn/Nhỏ",
  "Sum of Top Two Big/Small": "Tổng của hai số lớn/nhỏ hàng đầu",

  "Sum of Top Two Dragon/Tiger": "Tổng hai lá bài trên Rồng/Hổ",
  "Sum of Top Two Odd/Even": "Tổng hai lá bài trên Chẵn/Lẻ",
  "1st Dragon/Tiger": "Rồng/Hổ thứ nhất",
  "2nd Dragon/Tiger": "Rồng/Hổ thứ hai",
  "3rd Dragon/Tiger": "Rồng/Hổ thứ ba",
  "4th Dragon/Tiger": "Rồng/Hổ thứ tư",
  "5th Dragon/Tiger": "Rồng/Hổ thứ năm",
  "6th Odd/Even": "Chẵn/Lẻ thứ sáu",
  "6th Big/Small": "Lớn/Nhỏ thứ sáu",
  "6th Dragon/Tiger": "Rồng/Hổ thứ sáu",
  "7th Dragon/Tiger": "Rồng/Hổ thứ bảy",
  "7th Odd/Even": "Chẵn/Lẻ thứ bảy",
  "7th Big/Small": "Lớn/Nhỏ thứ bảy",
  "8th Big/Small": "Lớn/Nhỏ thứ tám",
  "8th Odd/Even": "Chẵn/Lẻ thứ tám",
  "8th Dragon/Tiger": "Rồng/Hổ thứ tám",
  "9th Odd/Even": "Chẵn/Lẻ thứ chín",
  "9th Big/Small": "Lớn/Nhỏ thứ chín",
  "10th Big/Small": "Lớn/Nhỏ thứ mười",
  "10th Odd/Even": "Chẵn/Lẻ thứ mười",
  "10th Dragon/Tiger": "Rồng/Hổ thứ mười",

  "1st B/S Sum": "Tổng B/S thứ 1",
  "1st O/E Sum": "Tổng O/E thứ 1",
  "1st B/S Tail Sum": "Tổng đuôi B/S thứ 1",
  "1st P/C Tail Sum": "Tổng đuôi P/C thứ 1",
  "2nd B/S Sum": "Tổng B/S thứ 2",
  "2nd O/E Sum": "Tổng O/E thứ 2",
  "2nd B/S Tail Sum": "Tổng đuôi B/S thứ 2",
  "2nd P/C Tail Sum": "Tổng đuôi P/C thứ 2",
  "3rd B/S Sum": "Tổng B/S thứ 3",
  "3rd O/E Sum": "Tổng O/E thứ 3",
  "3rd B/S Tail Sum": "Tổng đuôi B/S thứ 3",
  "3rd P/C Tail Sum": "Tổng đuôi P/C thứ 3",
  "1st/2nd Big/Small": "Lớn/Nhỏ thứ 1/2",
  "1st/2nd Odd/Even": "Lẻ/Chẵn thứ 1/2",

  "1st/2nd P/C": "1st/2nd Chẵn/Lẻ",
  "1st/2nd B/S Sum": "Tổng 1st/2nd Lớn/Nhỏ",
  "1st/2nd O/E Sum": "Tổng 1st/2nd Chẵn/Lẻ",
  "1st/2nd B/S Tail Sum": "Tổng Đuôi 1st/2nd Lớn/Nhỏ",
  "1st/2nd P/C Tail Sum": "Tổng Đuôi 1st/2nd Chẵn/Lẻ",
  "1st/3rd Big/Small": "1st/3rd Lớn/Nhỏ ",
  "1st/3rd Odd/Even": "1st/3rd Chẵn/Lẻ ",
  "1st/3rd P/C": "1st/3rd Chẵn/Lẻ ",
  "1st/3rd B/S Sum": "Tổng 1st/3rd Lớn/Nhỏ",

  "1st/3rd O/E Sum": "Tổng Chẵn/Lẻ 1st/3rd",
  "1st/3rd B/S Tail Sum": "Tổng Đuôi Lớn/Nhỏ 1st/3rd",
  "1st/3rd P/C Tail Sum": "Tổng Đuôi Chẵn/Lẻ 1st/3rd",
  "2nd/3rd Big/Small": "Lớn/Nhỏ 2nd/3rd",
  "2nd/3rd Odd/Even": "Chẵn/Lẻ 2nd/3rd",
  "2nd/3rd P/C": "Chẵn/Lẻ 2nd/3rd",
  "2nd/3rd B/S Sum": "Tổng Lớn/Nhỏ 2nd/3rd",
  "2nd/3rd O/E Sum": "Tổng Chẵn/Lẻ 2nd/3rd",

  "2nd/3rd B/S Tail Sum": "Tổng Đuôi Lớn/Nhỏ 2nd/3rd",
  "2nd/3rd P/C Tail Sum": "Tổng Đuôi Chẵn/Lẻ 2nd/3rd",
  "1st/2nd/3rd Big/Small": "Lớn/Nhỏ 1st/2nd/3rd",
  "1st/2nd/3rd Odd/Even": "Chẵn/Lẻ 1st/2nd/3rd",
  "1st/2nd/3rd P/C": "Chẵn/Lẻ 1st/2nd/3rd",
  "1st/2nd/3rd B/S Sum": "Tổng Lớn/Nhỏ 1st/2nd/3rd",
  "1st/2nd/3rd O/E Sum": "Tổng Chẵn/Lẻ 1st/2nd/3rd",
  "1st/2nd/3rd B/S Tail Sum": "Tổng Đuôi Lớn/Nhỏ 1st/2nd/3rd",
  "1st/2nd/3rd P/C Tail Sum": "Tổng Đuôi Chẵn/Lẻ 1st/2nd/3rd",

  "Extra No. Big/Small": "Số phụ Lớn/Nhỏ",
  "Extra No. Odd/Even": "Số phụ Lẻ/Chẵn",
  "Extra No. B/S Sum": "Tổng Số phụ Lớn/Nhỏ",
  "Extra No. O/E Sum": "Tổng Số phụ Lẻ/Chẵn",
  "Extra No. Sky/Ground": "Số phụ Trời/Đất",
  "Extra No. First/Last": "Số phụ Đầu/Cuối",
  "Extra No. Poultry/Beast": "Số phụ Gia cầm/Thú",
  "Extra No. Tail B/S": "Số phụ Đuôi Lớn/Nhỏ",
  "Extra No. Big/Small(No Tie)": "Số phụ Lớn/Nhỏ (Không Hòa)",

  "Ball 1 Big/Small": "Bóng 1 Lớn/Nhỏ",
  "Ball 1 Odd/Even": "Bóng 1 Lẻ/Chẵn",
  "Ball 1 B/S Sum": "Tổng Bóng 1 Lớn/Nhỏ",
  "Ball 1 O/E Sum": "Tổng Bóng 1 Lẻ/Chẵn",
  "Ball 1 Sky/Ground": "Bóng 1 Trời/Đất",
  "Ball 1 First/Last": "Bóng 1 Đầu/Cuối",
  "Ball 1 Poultry/Beast": "Bóng 1 Gia Cầm/Thú",
  "Ball 1 Tail B/S": "Đuôi Bóng 1 Lớn/Nhỏ",
  "Ball 1 Big/Small(No Tie)": "Bóng 1 Lớn/Nhỏ (Không Hòa)",
  "Ball 2 Big/Small": "Bóng 2 Lớn/Nhỏ",
  "Ball 2 Odd/Even": "Bóng 2 Lẻ/Chẵn",
  "Ball 2 B/S Sum": "Tổng Bóng 2 Lớn/Nhỏ",
  "Ball 2 O/E Sum": "Tổng Bóng 2 Lẻ/Chẵn",
  "Ball 2 Sky/Ground": "Bóng 2 Trời/Đất",

  "Ball 2 First/Last": "Quả bóng 2 Đầu/Tiếp theo",
  "Ball 2 Poultry/Beast": "Quả bóng 2 Gia cầm/Thú vật",
  "Ball 2 Tail B/S": "Quả bóng 2 Đuôi B/S",
  "Ball 2 Big/Small(No Tie)": "Quả bóng 2 Lớn/Nhỏ (Không Hòa)",
  "Ball 3 Big/Small": "Quả bóng 3 Lớn/Nhỏ",
  "Ball 3 Odd/Even": "Bóng 3 Chẵn/Lẻ",
  "Ball 3 B/S Sum": "Tổng Bóng 3 B/S",
  "Ball 3 O/E Sum": "Tổng Bóng 3 Chẵn/Lẻ",
  "Ball 3 Sky/Ground": "Jumlah Ganjil/Genap Bola 3",

  "Ball 3 First/Last": "Bóng 3 Đầu/Cuối",
  "Ball 3 Poultry/Beast": "Bóng 3 Gia cầm/Thú",
  "Ball 3 Tail B/S": "Bóng 3 Đuôi Lớn/Nhỏ",
  "Ball 3 Big/Small(No Tie)": "Bóng 3 Lớn/Nhỏ (Không Hòa)",
  "First": "Đầu tiên",
  "Last": "Cuối cùng",
  "Poultry": "Gia cầm",

  "Beast": "Quái thú",
  "Sky": "Bầu trời",
  "Ground": "Mặt đất",
  "Tail": "Đuôi",
  "Big(No Tie)": "Lớn (Không hòa)",
  "Small(No Tie)": "Nhỏ (Không hòa)",
  "Ball 4 Big/Small": "Bóng 4 Lớn/Nhỏ",
  "Ball 4 Odd/Even": "Bóng 4 Lẻ/Chẵn",

  "Ball 4 B/S Sum": "Tổng B/S bóng 4",
  "Ball 4 O/E Sum": "Tổng Chẵn/Lẻ bóng 4",
  "Ball 4 Sky/Ground": "Bóng 4 Trời/Đất",
  "Ball 4 First/Last": "Bóng 4 Đầu/Cuối",
  "Ball 4 Poultry/Beast": "Bóng 4 Gia cầm/Thú",
  "Ball 4 Tail B/S": "Đuôi bóng 4 B/S",
  "Ball 4 Big/Small(No Tie)": "Bóng 4 Lớn/Nhỏ (Không hòa)",
  "Ball 5 Big/Small": "Besar/Kecil bola 5",
  "Ball 5 Odd/Even": "Ganjil/Genap bola 5",

  "Ball 5 B/S Sum": "Jumlah B/S Bola 5",
  "Ball 5 O/E Sum": "Tổng Chẵn/Lẻ của Bóng 5",
  "Ball 5 Sky/Ground": "Bầu Trời/Mặt Đất của Bóng 5",
  "Ball 5 First/Last": "Đầu/Cuối của Bóng 5",
  "Ball 5 Poultry/Beast": "Unggas/Binatang",
  "Ball 5 Tail B/S": "Ekor B/S",
  "Ball 5 Big/Small(No Tie)": "Lớn/Nhỏ của Bóng 5 (Không Hòa)",

  "Ball 6 Big/Small": "Lớn/Nhỏ",
  "Ball 6 Odd/Even": "Lẻ/Chẵn",
  "Ball 6 B/S Sum": "Tổng Lớn/Nhỏ",
  "Ball 6 O/E Sum": "Tổng Lẻ/Chẵn",
  "Ball 6 Sky/Ground": "Trời/Đất",
  "Ball 6 First/Last": "Đầu/Cuối",
  "Ball 6 Poultry/Beast": "Gia cầm/Thú",
  "Ball 6 Tail B/S": "Đuôi Lớn/Nhỏ",
  "Ball 6 Big/Small(No Tie)": "Lớn/Nhỏ(Không Hòa)",

  "Sum B/S Sum": "Tổng B/S",
  "Sum O/E Sum": "Tổng Chẵn/Lẻ",
  "Sum Sky/Ground": "Tổng Trời/Đất",
  "Sum First/Last": "Tổng Đầu/Cuối",
  "Sum Poultry/Beast": "Tổng Gia Cầm/Thú",
  "Sum Tail B/S": "Tổng Đuôi Lớn/Nhỏ",
  "Sum Big/Small(No Tie)": "Tổng Lớn/Nhỏ (Không Hòa)",
  "Zodiac No. Big/Small": "Số Cung Hoàng Đạo Lớn/Nhỏ",
  "Zodiac No. Odd/Even": "Số Cung Hoàng Đạo Chẵn/Lẻ",

  "Zodiac No. B/S Sum": "Zodiac No. B/S Tổng",
  "Zodiac No. O/E Sum": "Zodiac No. O/E Tổng",
  "Zodiac No. Sky/Ground": "Zodiac No. Trời/Đất",
  "Zodiac No. First/Last": "Zodiac No. Đầu/Cuối",
  "Zodiac No. Poultry/Beast": "Zodiac No. Gia cầm/Thú",
  "Zodiac No. Tail B/S": "Zodiac No. Đuôi B/S",
  "Zodiac No. Big/Small(No Tie)": "Zodiac No. Lớn/Nhỏ (Không hòa)",
  "More First": "Nhiều Đầu",
  "More Last": "Nhiều Cuối",
  "More Odd": "Nhiều Lẻ",
  "More Even": "Nhiều Chẵn",
  "Sum More First/Last": "Tổng nhiều Đầu/Cuối",
  "Sum More Odd/Even": "Tổng nhiều Lẻ/Chẵn",
  "": "",
  "": "",
  "": "",
  "": "",
  "": "",
  "": ""
}
