


{
    
 "Draw": "Ziehen",
  "Winning No.": "Gewinnnummer",
  "Sum": "Summe",
  "D/T/T": "D/T/T",
  "First 3": "Erste 3",
  "Mid 3": "Mittlere 3",
  "Tiger": "Tiger",
  "Tie": "Unentschieden",
  "Dragon": "Drache",
  "Mixed 6": "Gemischte 6",
  "Pair": "Paar",
  "Half Streak": "Halbe Serie",
  "Straight": "Gerade",
  "Toak": "Toak",
  "Big": "Groß",
  "Odd": "Ungerade",
  "Even": "Gerade",
  "Small": "Klein",
  "Prime": "Primzahl",
  "Composite": "Zusammengesetzt",
  "Streak": "Serie",
  "Sum of Top Two": "Summe der oberen zwei",
  "B": "B",
  "O": "O",
  "E": "E",
  "S": "S",
  "B/S": "B/S",
  "O/E": "O/E",
  "Fish/Prawn/Crab": "Fisch/Garnele/Krabbe",
  "Fish": "Fisch",
  "Prawn": "Garnele",
  "Crab": "Krabbe",
  "Shrimp": "Shrimp",
  "Rooster": "Hahn",
  "Cash": "Bargeld",
  "Gourd": "Kürbis",
  "Ball 1": "Ball 1",
  "Ball 2": "Ball 2",
  "Ball 3": "Ball 3",
  "Ball 4": "Ball 4",
  "Ball 5": "Ball 5",
  "Ball 6": "Ball 6",
  "Zodiac No.": "Tierkreisnummer",
  "Tail": "Schwanz",
  "B/S(No Tie)": "B/S (Kein Unentschieden)",
  "F/L": "F/L",
  "B E": "B E",
  "S E": "S E",
  "S O": "S O",
  "B O": "B O",
  "First": "Erste",
  "Last": "Letzte",
  "Earth": "Erde",
       "5 elements":"fünf Elemente",
       "":"",
       "":"",
       "":"",
       "":"",
       "":"",
       "":"",
       "":"",
       "":"",
       "":"",
       "":"",
       "":"",
       "":"",
       "":"",
       "":"",
       "":"",
       "":"",
       "":"",
       "":"",
       "":"",
       "":"",
       "":"",
       "":"",
       "":"",
       "":"",
       "":"",
       "":"",
       "":"",
       "":"",
       "":"",
       "":"",
       "":"",
       "":"",
       "":"",
       "":"",
       "":"",
       "":"",
       "":"",
       "":"",
       "":"",
       "":"",
       "":"",
       "":"",
       "":"",
       "":"",
       "":"",
       "":""
   }